chatfic_validator/__init__.py
chatfic_validator/error.py
chatfic_validator/result.py
chatfic_validator/validator.py
chatfic_validator-0.2.4.dist-info/licenses/LICENSE
tests/__init__.py
tests/test_validator.py
chatfic_validator-0.2.4.dist-info/METADATA
chatfic_validator-0.2.4.dist-info/WHEEL
chatfic_validator-0.2.4.dist-info/top_level.txt
chatfic_validator-0.2.4.dist-info/RECORD
