Metadata-Version: 2.4
Name: chatfic-validator
Version: 0.2.4
Summary: A Python package for validating chatfic-format data
Home-page: https://github.com/gokhanmeteerturk/chatfic-validator-python
Author: Gökhan Mete Ertürk
Author-email: 8rlvjfxsh@mozmail.com
License: MIT
Classifier: Programming Language :: Python :: 3
Classifier: License :: OSI Approved :: GNU General Public License v3 (GPLv3)
Classifier: Operating System :: OS Independent
Requires-Python: >=3.6
License-File: LICENSE
Dynamic: author
Dynamic: author-email
Dynamic: classifier
Dynamic: description
Dynamic: description-content-type
Dynamic: home-page
Dynamic: license
Dynamic: license-file
Dynamic: requires-python
Dynamic: summary
